damensm_profiling/__init__.py
damensm_profiling/main.py
damensm_profiling-0.1.11.dist-info/METADATA
damensm_profiling-0.1.11.dist-info/WHEEL
damensm_profiling-0.1.11.dist-info/top_level.txt
damensm_profiling-0.1.11.dist-info/RECORD
