Metadata-Version: 2.4
Name: damensm_profiling
Version: 0.1.11
Summary: Damen-library
Author-email: giandaeky <giandaekyoga10@gmail.com>
License: MIT
Requires-Python: >=3.8
